fft.py
fft_gyujin.py
fft_gyujin-1.0.0.dist-info/METADATA
fft_gyujin-1.0.0.dist-info/WHEEL
fft_gyujin-1.0.0.dist-info/top_level.txt
fft_gyujin-1.0.0.dist-info/RECORD
