Metadata-Version: 2.1
Name: fft-gyujin
Version: 1.0.0
Summary: fft
Home-page: UNKNOWN
Author: gyujin
Author-email: limmok0731@naver.com
License: MIT
Platform: UNKNOWN
